cereja_ai/__init__.py
cereja_ai/losses/__init__.py
cereja_ai/losses/timeseries.py
cereja_ai/metrics/__init__.py
cereja_ai/metrics/timeseries.py
cereja_ai/vision/__init__.py
cereja_ai/vision/_base.py
cereja_ai/vision/utils.py
cereja_ai-0.0.5.dist-info/LICENSE
cereja_ai-0.0.5.dist-info/METADATA
cereja_ai-0.0.5.dist-info/WHEEL
cereja_ai-0.0.5.dist-info/top_level.txt
cereja_ai-0.0.5.dist-info/RECORD
