Metadata-Version: 2.1
Name: cereja-ai
Version: 0.0.5
Summary: Cereja-AI is a lib that makes available AI model architectures and pre-trained models for diverse usage.
Author-email: Joab Leite <leitejoab@gmail.com>
License: MIT License
Project-URL: Homepage, https://github.com/cereja-project/cereja-ai
Project-URL: Bug Tracker, https://github.com/cereja-project/cereja-ai/issues/new/choose
Keywords: tensorflow,keras,models
Classifier: Programming Language :: Python :: 3
Classifier: Programming Language :: Python :: 3.6
Classifier: Programming Language :: Python :: 3.7
Classifier: Programming Language :: Python :: 3.8
Classifier: Programming Language :: Python :: 3.9
Classifier: Programming Language :: Python :: 3.10
Classifier: Programming Language :: Python :: 3.11
Classifier: Programming Language :: Python :: 3 :: Only
Classifier: License :: OSI Approved :: MIT License
Classifier: Operating System :: OS Independent
Requires-Python: >=3.6
License-File: LICENSE
Requires-Dist: cereja (==1.8.4)
Requires-Dist: tensorflow
Requires-Dist: numpy
Requires-Dist: calango
Requires-Dist: mediapipe
Requires-Dist: opencv-python (~=4.7.0.72)
